{
  "agency_id": "YRTA", 
  "color": "405CAA", 
  "name": "(\u1043\u1046 \u1021\u1031\u102c\u1004\u103a\u1019\u1004\u103a\u1039\u1002\u101c\u102c) \u1021\u1031\u102c\u1004\u103a\u1019\u1004\u103a\u1039\u1002\u101c\u102c - \u1006\u1030\u1038\u101c\u1031", 
  "route_id": "36-AungMingalar", 
  "shape": {
    "geometry": {
      "coordinates": [
        [
          96.15529, 
          16.92829
        ], 
        [
          96.15573, 
          16.92758
        ], 
        [
          96.1566, 
          16.92562
        ], 
        [
          96.15683, 
          16.9253
        ], 
        [
          96.16181, 
          16.92051
        ], 
        [
          96.16261, 
          16.91946
        ], 
        [
          96.16541, 
          16.91288
        ], 
        [
          96.1659, 
          16.91089
        ], 
        [
          96.16622, 
          16.90863
        ], 
        [
          96.16614, 
          16.90712
        ], 
        [
          96.16587, 
          16.90535
        ], 
        [
          96.16541, 
          16.90382
        ], 
        [
          96.1648, 
          16.90239
        ], 
        [
          96.1642, 
          16.90138
        ], 
        [
          96.16291, 
          16.89976
        ], 
        [
          96.16173, 
          16.89856
        ], 
        [
          96.1543, 
          16.8923
        ], 
        [
          96.15399, 
          16.89187
        ], 
        [
          96.15372, 
          16.89121
        ], 
        [
          96.15367, 
          16.89078
        ], 
        [
          96.15379, 
          16.88922
        ], 
        [
          96.15412, 
          16.8884
        ], 
        [
          96.15463, 
          16.8841
        ], 
        [
          96.15547, 
          16.88141
        ], 
        [
          96.15703, 
          16.87263
        ], 
        [
          96.15753, 
          16.87041
        ], 
        [
          96.15723, 
          16.87005
        ], 
        [
          96.15591, 
          16.86977
        ], 
        [
          96.15564, 
          16.86961
        ], 
        [
          96.15475, 
          16.86733
        ], 
        [
          96.15456, 
          16.86637
        ], 
        [
          96.15402, 
          16.86583
        ], 
        [
          96.15465, 
          16.86516
        ], 
        [
          96.15483, 
          16.86479
        ], 
        [
          96.15527, 
          16.86204
        ], 
        [
          96.15727, 
          16.85375
        ], 
        [
          96.15759, 
          16.85058
        ], 
        [
          96.15481, 
          16.83122
        ], 
        [
          96.15385, 
          16.82356
        ], 
        [
          96.1543, 
          16.82222
        ], 
        [
          96.15637, 
          16.81878
        ], 
        [
          96.15645, 
          16.81845
        ], 
        [
          96.15582, 
          16.81442
        ], 
        [
          96.15585, 
          16.81256
        ], 
        [
          96.15607, 
          16.81087
        ], 
        [
          96.15592, 
          16.80968
        ], 
        [
          96.15569, 
          16.80931
        ], 
        [
          96.15476, 
          16.80831
        ], 
        [
          96.1546, 
          16.80806
        ], 
        [
          96.15451, 
          16.80751
        ], 
        [
          96.15596, 
          16.80486
        ], 
        [
          96.15596, 
          16.80391
        ], 
        [
          96.15551, 
          16.80306
        ], 
        [
          96.15557, 
          16.80278
        ], 
        [
          96.1577, 
          16.80158
        ], 
        [
          96.15801, 
          16.80126
        ], 
        [
          96.15838, 
          16.80049
        ], 
        [
          96.1573, 
          16.79841
        ], 
        [
          96.15625, 
          16.79556
        ], 
        [
          96.15649, 
          16.7952
        ], 
        [
          96.15652, 
          16.79499
        ], 
        [
          96.15635, 
          16.7937
        ], 
        [
          96.15639, 
          16.79297
        ], 
        [
          96.15698, 
          16.79046
        ], 
        [
          96.15745, 
          16.78781
        ], 
        [
          96.15734, 
          16.78718
        ], 
        [
          96.15647, 
          16.78591
        ], 
        [
          96.15813, 
          16.78371
        ], 
        [
          96.15886, 
          16.78323
        ], 
        [
          96.15901, 
          16.78284
        ], 
        [
          96.15873, 
          16.77515
        ], 
        [
          96.15823, 
          16.77441
        ], 
        [
          96.15841, 
          16.77407
        ], 
        [
          96.15881, 
          16.77393
        ], 
        [
          96.15917, 
          16.7741
        ], 
        [
          96.1593, 
          16.77435
        ], 
        [
          96.15884, 
          16.77512
        ], 
        [
          96.15895, 
          16.77876
        ], 
        [
          96.1591, 
          16.77935
        ], 
        [
          96.15918, 
          16.78149
        ], 
        [
          96.15971, 
          16.78251
        ], 
        [
          96.15959, 
          16.78389
        ], 
        [
          96.1599, 
          16.78463
        ], 
        [
          96.15992, 
          16.78491
        ], 
        [
          96.15985, 
          16.78519
        ], 
        [
          96.15863, 
          16.78589
        ], 
        [
          96.15808, 
          16.78631
        ], 
        [
          96.15786, 
          16.78654
        ], 
        [
          96.15769, 
          16.78692
        ], 
        [
          96.15716, 
          16.79019
        ], 
        [
          96.15657, 
          16.79275
        ], 
        [
          96.15648, 
          16.79369
        ], 
        [
          96.15664, 
          16.79517
        ], 
        [
          96.15681, 
          16.79553
        ], 
        [
          96.15664, 
          16.79598
        ], 
        [
          96.15669, 
          16.79645
        ], 
        [
          96.15739, 
          16.79839
        ], 
        [
          96.15846, 
          16.80045
        ], 
        [
          96.15799, 
          16.80147
        ], 
        [
          96.15635, 
          16.80252
        ], 
        [
          96.1557, 
          16.80281
        ], 
        [
          96.15564, 
          16.80302
        ], 
        [
          96.15591, 
          16.80346
        ], 
        [
          96.15604, 
          16.80391
        ], 
        [
          96.15603, 
          16.80503
        ], 
        [
          96.15467, 
          16.80745
        ], 
        [
          96.1548, 
          16.80809
        ], 
        [
          96.15593, 
          16.80939
        ], 
        [
          96.15608, 
          16.80986
        ], 
        [
          96.15618, 
          16.811
        ], 
        [
          96.15598, 
          16.81215
        ], 
        [
          96.1559, 
          16.81431
        ], 
        [
          96.15619, 
          16.81644
        ], 
        [
          96.15656, 
          16.81828
        ], 
        [
          96.15646, 
          16.81882
        ], 
        [
          96.15446, 
          16.82203
        ], 
        [
          96.15417, 
          16.82265
        ], 
        [
          96.15394, 
          16.82363
        ], 
        [
          96.15489, 
          16.83123
        ], 
        [
          96.15767, 
          16.85069
        ], 
        [
          96.15734, 
          16.85376
        ], 
        [
          96.15571, 
          16.86054
        ], 
        [
          96.15495, 
          16.86471
        ], 
        [
          96.15474, 
          16.86522
        ], 
        [
          96.15446, 
          16.86558
        ], 
        [
          96.15475, 
          16.86733
        ], 
        [
          96.15553, 
          16.86946
        ], 
        [
          96.15591, 
          16.86977
        ], 
        [
          96.15723, 
          16.87005
        ], 
        [
          96.15753, 
          16.87041
        ], 
        [
          96.15541, 
          16.8822
        ], 
        [
          96.15473, 
          16.88414
        ], 
        [
          96.1539, 
          16.8912
        ], 
        [
          96.15414, 
          16.89187
        ], 
        [
          96.15465, 
          16.89247
        ], 
        [
          96.16145, 
          16.89818
        ], 
        [
          96.16337, 
          16.90013
        ], 
        [
          96.16413, 
          16.90113
        ], 
        [
          96.16466, 
          16.90195
        ], 
        [
          96.16558, 
          16.90405
        ], 
        [
          96.16608, 
          16.90603
        ], 
        [
          96.16628, 
          16.90868
        ], 
        [
          96.16598, 
          16.91091
        ], 
        [
          96.16548, 
          16.9129
        ], 
        [
          96.16264, 
          16.91949
        ], 
        [
          96.16184, 
          16.92054
        ], 
        [
          96.15705, 
          16.92515
        ], 
        [
          96.15654, 
          16.9258
        ], 
        [
          96.15573, 
          16.92758
        ], 
        [
          96.1553, 
          16.92826
        ]
      ], 
      "type": "LineString"
    }, 
    "properties": {}, 
    "type": "Feature"
  }, 
  "stops": [
    812, 
    809, 
    819, 
    2401, 
    850, 
    858, 
    843, 
    864, 
    866, 
    862, 
    883, 
    888, 
    886, 
    890, 
    1275, 
    1821, 
    1280, 
    1818, 
    1239, 
    1236, 
    36, 
    1242, 
    1246, 
    2424, 
    324, 
    322, 
    230, 
    209, 
    202, 
    194, 
    144, 
    141, 
    195, 
    203, 
    208, 
    210, 
    2425, 
    321, 
    323, 
    325, 
    1245, 
    1241, 
    37, 
    1817, 
    1238, 
    1240, 
    38, 
    1281, 
    1274, 
    889, 
    885, 
    887, 
    882, 
    861, 
    865, 
    863, 
    842, 
    857, 
    849, 
    1823, 
    818, 
    810, 
    813
  ]
}